pointcloudlib/__init__.py
pointcloudlib/depth_estimation.py
pointcloudlib/full_pipeline.py
pointcloudlib/point_cloud_aligner.py
pointcloudlib/point_cloud_generator.py
pointcloudlib/utils.py
pointcloudlib-0.1.3.dist-info/licenses/LICENSE
pointcloudlib-0.1.3.dist-info/METADATA
pointcloudlib-0.1.3.dist-info/WHEEL
pointcloudlib-0.1.3.dist-info/top_level.txt
pointcloudlib-0.1.3.dist-info/RECORD
