Metadata-Version: 2.4
Name: pointcloudlib
Version: 0.1.3
Summary: Python library for image processing, focused on 3D environment modeling. This project is part of the final graduation project at the Costa Rica Institute of Technology.
Author: Yordi Brenes Roda
Author-email: ybrenesr@estudiantec.cr
Classifier: Programming Language :: Python :: 3
Classifier: License :: OSI Approved :: MIT License
License-File: LICENSE
Dynamic: author
Dynamic: author-email
Dynamic: classifier
Dynamic: description
Dynamic: description-content-type
Dynamic: license-file
Dynamic: summary
